x_1000/__init__.py
x_1000/outer_models.py
x_1000/outer_rim.py
x_1000/skeleton.py
x_1000-0.1.0.dist-info/LICENSE
x_1000-0.1.0.dist-info/METADATA
x_1000-0.1.0.dist-info/WHEEL
x_1000-0.1.0.dist-info/top_level.txt
x_1000-0.1.0.dist-info/RECORD
